__init__.py
aws_to_dg.py
schema_normalization-0.1.0.dist-info/METADATA
schema_normalization-0.1.0.dist-info/WHEEL
schema_normalization-0.1.0.dist-info/top_level.txt
schema_normalization-0.1.0.dist-info/RECORD
