Metadata-Version: 2.4
Name: schema-normalization
Version: 0.1.0
Summary: Package for converting AWS Transcribe JSON data into Deepgram JSON data
Requires-Python: >=3.12
Requires-Dist: pydantic
